noisemonitor/__init__.py
noisemonitor/profile.py
noisemonitor/summary.py
noisemonitor/util/__init__.py
noisemonitor/util/core.py
noisemonitor/util/display.py
noisemonitor/util/filter.py
noisemonitor/util/load.py
noisemonitor/weather/__init__.py
noisemonitor/weather/weathercan.py
noisemonitor-1.0.1.dist-info/licenses/LICENSE
noisemonitor-1.0.1.dist-info/METADATA
noisemonitor-1.0.1.dist-info/WHEEL
noisemonitor-1.0.1.dist-info/top_level.txt
noisemonitor-1.0.1.dist-info/RECORD
