Metadata-Version: 2.4
Name: noisemonitor
Version: 1.0.1
Summary: Long-term sound level measurements analysis in Python
Author-email: Valérian Fraisse <valerian.fraisse@mail.mcgill.ca>
Project-URL: Homepage, https://github.com/valerianF/noisemonitor
Project-URL: Bug Tracker, https://github.com/valerianF/noisemonitor/issues
Classifier: Programming Language :: Python :: 3
Classifier: License :: OSI Approved :: Apache Software License
Classifier: Operating System :: OS Independent
Requires-Python: >=3.8
License-File: LICENSE
Requires-Dist: matplotlib>=3.5.3
Requires-Dist: numpy>=1.21.6
Requires-Dist: pandas>=1.3.5
Requires-Dist: xlrd>=2.0.1
Requires-Dist: openpyxl>=3.1.2
Provides-Extra: weather
Requires-Dist: requests>=2.25.0; extra == "weather"
Requires-Dist: aiohttp>=3.8.0; extra == "weather"
Requires-Dist: lxml>=4.6.0; extra == "weather"
Requires-Dist: python-dateutil>=2.8.0; extra == "weather"
Dynamic: license-file
